odoo/addons/sale_coupon_reward_fixed_price/README.rst
odoo/addons/sale_coupon_reward_fixed_price/__init__.py
odoo/addons/sale_coupon_reward_fixed_price/__manifest__.py
odoo/addons/sale_coupon_reward_fixed_price/i18n/it.po
odoo/addons/sale_coupon_reward_fixed_price/i18n/sale_coupon_reward_fixed_price.pot
odoo/addons/sale_coupon_reward_fixed_price/models/__init__.py
odoo/addons/sale_coupon_reward_fixed_price/models/coupon_program.py
odoo/addons/sale_coupon_reward_fixed_price/models/coupon_reward.py
odoo/addons/sale_coupon_reward_fixed_price/models/sale_order.py
odoo/addons/sale_coupon_reward_fixed_price/readme/CONFIGURE.rst
odoo/addons/sale_coupon_reward_fixed_price/readme/CONTRIBUTORS.rst
odoo/addons/sale_coupon_reward_fixed_price/readme/CREDITS.rst
odoo/addons/sale_coupon_reward_fixed_price/readme/DESCRIPTION.rst
odoo/addons/sale_coupon_reward_fixed_price/readme/USAGE.rst
odoo/addons/sale_coupon_reward_fixed_price/static/description/icon.png
odoo/addons/sale_coupon_reward_fixed_price/static/description/index.html
odoo/addons/sale_coupon_reward_fixed_price/tests/__init__.py
odoo/addons/sale_coupon_reward_fixed_price/tests/test_sale_coupon_fixed_price.py
odoo/addons/sale_coupon_reward_fixed_price/views/coupon_program_view.xml
odoo14_addon_sale_coupon_reward_fixed_price-14.0.1.1.0.dist-info/METADATA
odoo14_addon_sale_coupon_reward_fixed_price-14.0.1.1.0.dist-info/WHEEL
odoo14_addon_sale_coupon_reward_fixed_price-14.0.1.1.0.dist-info/top_level.txt
odoo14_addon_sale_coupon_reward_fixed_price-14.0.1.1.0.dist-info/RECORD
